mps_deform_conv/_C.cpython-314-darwin.so
mps_deform_conv/__init__.py
mps_deform_conv/csrc/deform_conv2d_mps.mm
mps_deform_conv/kernels/deform_conv2d.metal
mps_deform_conv-0.1.4.dist-info/METADATA
mps_deform_conv-0.1.4.dist-info/WHEEL
mps_deform_conv-0.1.4.dist-info/top_level.txt
mps_deform_conv-0.1.4.dist-info/RECORD
