Metadata-Version: 2.4
Name: mps-deform-conv
Version: 0.1.4
Summary: Deformable Convolution 2D for PyTorch on Apple Silicon (MPS)
Author: imperatormk
License-Expression: MIT
Project-URL: Homepage, https://github.com/mpsops/mps-deform-conv
Project-URL: Repository, https://github.com/mpsops/mps-deform-conv
Project-URL: Issues, https://github.com/mpsops/mps-deform-conv/issues
Keywords: deformable-convolution,dcn,apple-silicon,pytorch,mps,metal,detr,basicvsr
Classifier: Development Status :: 3 - Alpha
Classifier: Intended Audience :: Developers
Classifier: Intended Audience :: Science/Research
Classifier: Operating System :: MacOS :: MacOS X
Classifier: Programming Language :: Python :: 3
Classifier: Programming Language :: Python :: 3.10
Classifier: Programming Language :: Python :: 3.11
Classifier: Programming Language :: Python :: 3.12
Classifier: Topic :: Scientific/Engineering :: Artificial Intelligence
Requires-Python: >=3.10
Requires-Dist: torch>=2.0.0
Dynamic: requires-python
